devpi_jenkins/__init__.py
devpi_jenkins/devpibootstrap.py.template
devpi_jenkins/main.py
devpi_jenkins-3.0.1.dist-info/METADATA
devpi_jenkins-3.0.1.dist-info/WHEEL
devpi_jenkins-3.0.1.dist-info/entry_points.txt
devpi_jenkins-3.0.1.dist-info/top_level.txt
devpi_jenkins-3.0.1.dist-info/RECORD
